Metadata-Version: 1.0
Name: xdnn
Version: 0.2
Summary: Explaining deep neural networks
Home-page: UNKNOWN
Author: Prashant K. Sharma
Author-email: prashaantsharmaa@gmail.com
License: MIT
Platform: UNKNOWN
